{
  "last_updated_utc": "2026-02-19T11:45:36.274734",
  "prices": [
    {
      "symbol": "^GSPC",
      "price": 6881.31,
      "change_percent": 0.56,
      "logo_url": null
    },
    {
      "symbol": "^IXIC",
      "price": 22753.63,
      "change_percent": 0.78,
      "logo_url": null
    },
    {
      "symbol": "^DJI",
      "price": 49662.66,
      "change_percent": 0.26,
      "logo_url": null
    },
    {
      "symbol": "^N225",
      "price": 57467.83,
      "change_percent": -0.01,
      "logo_url": null
    },
    {
      "symbol": "^HSI",
      "price": 26705.94,
      "change_percent": 0.52,
      "logo_url": null
    },
    {
      "symbol": "^FTSE",
      "price": 10610.56,
      "change_percent": -0.71,
      "logo_url": null
    },
    {
      "symbol": "^GDAXI",
      "price": 25103.73,
      "change_percent": -0.38,
      "logo_url": null
    },
    {
      "symbol": "^FCHI",
      "price": 8368.51,
      "change_percent": -0.52,
      "logo_url": null
    },
    {
      "symbol": "^STOXX50E",
      "price": 6060.23,
      "change_percent": -0.61,
      "logo_url": null
    },
    {
      "symbol": "^AXJO",
      "price": 9086.2,
      "change_percent": 0.88,
      "logo_url": null
    },
    {
      "symbol": "^BVSP",
      "price": 186016.0,
      "change_percent": 0.02,
      "logo_url": null
    }
  ],
  "failed_tickers": []
}