{
  "last_updated_utc": "2026-05-01T15:08:06.650837",
  "prices": [
    {
      "symbol": "^GSPC",
      "price": 7245.6,
      "change_percent": 0.15,
      "change_7d_percent": 1.12,
      "change_30d_percent": 10.19,
      "return_1y_percent": 22.58,
      "return_3y_percent": 20.12,
      "return_5y_percent": 11.5,
      "logo_url": null
    },
    {
      "symbol": "^IXIC",
      "price": 25094.29,
      "change_percent": 0.47,
      "change_7d_percent": 1.04,
      "change_30d_percent": 14.9,
      "return_1y_percent": 31.31,
      "return_3y_percent": 24.71,
      "return_5y_percent": 12.79,
      "logo_url": null
    },
    {
      "symbol": "^DJI",
      "price": 49748.76,
      "change_percent": -0.17,
      "change_7d_percent": 1.05,
      "change_30d_percent": 6.84,
      "return_1y_percent": 17.7,
      "return_3y_percent": 14.76,
      "return_5y_percent": 7.58,
      "logo_url": null
    },
    {
      "symbol": "^N225",
      "price": 59284.92,
      "change_percent": -0.34,
      "change_7d_percent": -0.51,
      "change_30d_percent": 10.32,
      "return_1y_percent": 64.53,
      "return_3y_percent": 27.12,
      "return_5y_percent": 15.77,
      "logo_url": null
    },
    {
      "symbol": "^HSI",
      "price": 25776.53,
      "change_percent": -0.89,
      "change_7d_percent": -0.54,
      "change_30d_percent": 4.14,
      "return_1y_percent": 16.55,
      "return_3y_percent": 9.02,
      "return_5y_percent": -2.47,
      "logo_url": null
    },
    {
      "symbol": "^FTSE",
      "price": 10366.84,
      "change_percent": -0.11,
      "change_7d_percent": -0.12,
      "change_30d_percent": 0.02,
      "return_1y_percent": 22.19,
      "return_3y_percent": 9.66,
      "return_5y_percent": 8.27,
      "logo_url": null
    },
    {
      "symbol": "^GDAXI",
      "price": 24292.38,
      "change_percent": 2.43,
      "change_7d_percent": 0.57,
      "change_30d_percent": 7.67,
      "return_1y_percent": 7.99,
      "return_3y_percent": 15.12,
      "return_5y_percent": 9.68,
      "logo_url": null
    },
    {
      "symbol": "^FCHI",
      "price": 8114.84,
      "change_percent": 1.91,
      "change_7d_percent": -1.37,
      "change_30d_percent": 4.41,
      "return_1y_percent": 6.87,
      "return_3y_percent": 2.7,
      "return_5y_percent": 4.79,
      "logo_url": null
    },
    {
      "symbol": "^STOXX50E",
      "price": 5881.51,
      "change_percent": 1.78,
      "change_7d_percent": -0.22,
      "change_30d_percent": 6.13,
      "return_1y_percent": 13.99,
      "return_3y_percent": 10.5,
      "return_5y_percent": 7.94,
      "logo_url": null
    },
    {
      "symbol": "^AXJO",
      "price": 8665.8,
      "change_percent": -0.24,
      "change_7d_percent": -1.45,
      "change_30d_percent": -0.07,
      "return_1y_percent": 6.64,
      "return_3y_percent": 5.84,
      "return_5y_percent": 3.95,
      "logo_url": null
    },
    {
      "symbol": "^BVSP",
      "price": 187318.0,
      "change_percent": 1.39,
      "change_7d_percent": -2.12,
      "change_30d_percent": 2.63,
      "return_1y_percent": 38.72,
      "return_3y_percent": 21.5,
      "return_5y_percent": 8.36,
      "logo_url": null
    }
  ],
  "failed_tickers": []
}