{
  "last_updated_utc": "2026-02-15T10:36:25.630293",
  "prices": [
    {
      "symbol": "^GSPC",
      "price": 6836.17,
      "change_percent": 0.03,
      "logo_url": null
    },
    {
      "symbol": "^IXIC",
      "price": 22546.67,
      "change_percent": -0.07,
      "logo_url": null
    },
    {
      "symbol": "^DJI",
      "price": 49500.93,
      "change_percent": 0.12,
      "logo_url": null
    },
    {
      "symbol": "^N225",
      "price": 56941.97,
      "change_percent": -0.45,
      "logo_url": null
    },
    {
      "symbol": "^HSI",
      "price": 26567.12,
      "change_percent": -0.27,
      "logo_url": null
    },
    {
      "symbol": "^FTSE",
      "price": 10446.4,
      "change_percent": 0.42,
      "logo_url": null
    },
    {
      "symbol": "^GDAXI",
      "price": 24914.88,
      "change_percent": 0.37,
      "logo_url": null
    },
    {
      "symbol": "^FCHI",
      "price": 8311.74,
      "change_percent": -0.05,
      "logo_url": null
    },
    {
      "symbol": "^STOXX50E",
      "price": 5985.23,
      "change_percent": -0.43,
      "logo_url": null
    },
    {
      "symbol": "^AXJO",
      "price": 8917.6,
      "change_percent": -1.39,
      "logo_url": null
    },
    {
      "symbol": "^BVSP",
      "price": 186464.0,
      "change_percent": -0.69,
      "logo_url": null
    }
  ],
  "failed_tickers": []
}