{
  "last_updated_utc": "2026-02-13T19:01:14.235106",
  "prices": [
    {
      "symbol": "^GSPC",
      "price": 6866.36,
      "change_percent": 0.47
    },
    {
      "symbol": "^IXIC",
      "price": 22687.09,
      "change_percent": 0.56
    },
    {
      "symbol": "^DJI",
      "price": 49596.37,
      "change_percent": 0.32
    },
    {
      "symbol": "^N225",
      "price": 56941.97,
      "change_percent": -0.45
    },
    {
      "symbol": "^HSI",
      "price": 26567.12,
      "change_percent": -0.27
    },
    {
      "symbol": "^FTSE",
      "price": 10446.35,
      "change_percent": 0.42
    },
    {
      "symbol": "^GDAXI",
      "price": 24914.88,
      "change_percent": 0.37
    },
    {
      "symbol": "^FCHI",
      "price": 8311.74,
      "change_percent": -0.05
    },
    {
      "symbol": "^STOXX50E",
      "price": 5985.23,
      "change_percent": -0.43
    },
    {
      "symbol": "^AXJO",
      "price": 8917.6,
      "change_percent": -1.39
    },
    {
      "symbol": "^BVSP",
      "price": 186365.39,
      "change_percent": -0.75
    }
  ],
  "failed_tickers": []
}