{
  "last_updated_utc": "2026-03-12T08:57:27.066016",
  "prices": [
    {
      "symbol": "^GSPC",
      "price": 6775.8,
      "change_percent": -0.08,
      "logo_url": null
    },
    {
      "symbol": "^IXIC",
      "price": 22716.13,
      "change_percent": 0.08,
      "logo_url": null
    },
    {
      "symbol": "^DJI",
      "price": 47417.27,
      "change_percent": -0.61,
      "logo_url": null
    },
    {
      "symbol": "^N225",
      "price": 54452.96,
      "change_percent": 0.12,
      "logo_url": null
    },
    {
      "symbol": "^HSI",
      "price": 25716.76,
      "change_percent": -0.01,
      "logo_url": null
    },
    {
      "symbol": "^FTSE",
      "price": 10282.55,
      "change_percent": -0.69,
      "logo_url": null
    },
    {
      "symbol": "^GDAXI",
      "price": 23509.34,
      "change_percent": -0.29,
      "logo_url": null
    },
    {
      "symbol": "^FCHI",
      "price": 7981.76,
      "change_percent": -0.31,
      "logo_url": null
    },
    {
      "symbol": "^STOXX50E",
      "price": 5744.8,
      "change_percent": -0.63,
      "logo_url": null
    },
    {
      "symbol": "^AXJO",
      "price": 8629.0,
      "change_percent": -1.31,
      "logo_url": null
    },
    {
      "symbol": "^BVSP",
      "price": 183969.0,
      "change_percent": 0.28,
      "logo_url": null
    }
  ],
  "failed_tickers": []
}