{
  "last_updated_utc": "2026-04-30T14:18:45.474371",
  "prices": [
    {
      "symbol": "^GSPC",
      "price": 7133.77,
      "change_percent": -0.39,
      "change_7d_percent": 0.36,
      "change_30d_percent": 12.45,
      "return_1y_percent": 28.12,
      "return_3y_percent": 19.6,
      "return_5y_percent": 11.35,
      "logo_url": null
    },
    {
      "symbol": "^IXIC",
      "price": 24528.75,
      "change_percent": -1.33,
      "change_7d_percent": 0.37,
      "change_30d_percent": 17.96,
      "return_1y_percent": 40.63,
      "return_3y_percent": 26.12,
      "return_5y_percent": 12.49,
      "logo_url": null
    },
    {
      "symbol": "^DJI",
      "price": 49339.64,
      "change_percent": 1.18,
      "change_7d_percent": 0.06,
      "change_30d_percent": 9.12,
      "return_1y_percent": 21.34,
      "return_3y_percent": 13.1,
      "return_5y_percent": 7.53,
      "logo_url": null
    },
    {
      "symbol": "^N225",
      "price": 59284.92,
      "change_percent": -0.34,
      "change_7d_percent": -0.51,
      "change_30d_percent": 14.26,
      "return_1y_percent": 64.53,
      "return_3y_percent": 27.12,
      "return_5y_percent": 15.77,
      "logo_url": null
    },
    {
      "symbol": "^HSI",
      "price": 25776.53,
      "change_percent": -0.89,
      "change_7d_percent": -0.54,
      "change_30d_percent": 4.14,
      "return_1y_percent": 16.55,
      "return_3y_percent": 9.02,
      "return_5y_percent": -2.47,
      "logo_url": null
    },
    {
      "symbol": "^FTSE",
      "price": 10359.71,
      "change_percent": 1.43,
      "change_7d_percent": -0.93,
      "change_30d_percent": 2.29,
      "return_1y_percent": 21.97,
      "return_3y_percent": 9.59,
      "return_5y_percent": 8.23,
      "logo_url": null
    },
    {
      "symbol": "^GDAXI",
      "price": 24109.06,
      "change_percent": 1.66,
      "change_7d_percent": -0.19,
      "change_30d_percent": 6.85,
      "return_1y_percent": 7.17,
      "return_3y_percent": 14.83,
      "return_5y_percent": 9.51,
      "logo_url": null
    },
    {
      "symbol": "^FCHI",
      "price": 8062.35,
      "change_percent": 1.25,
      "change_7d_percent": -2.01,
      "change_30d_percent": 3.73,
      "return_1y_percent": 6.17,
      "return_3y_percent": 2.48,
      "return_5y_percent": 4.65,
      "logo_url": null
    },
    {
      "symbol": "^STOXX50E",
      "price": 5835.32,
      "change_percent": 0.98,
      "change_7d_percent": -1.01,
      "change_30d_percent": 5.3,
      "return_1y_percent": 13.09,
      "return_3y_percent": 10.21,
      "return_5y_percent": 7.77,
      "logo_url": null
    },
    {
      "symbol": "^AXJO",
      "price": 8687.0,
      "change_percent": -0.27,
      "change_7d_percent": -1.77,
      "change_30d_percent": 2.67,
      "return_1y_percent": 6.64,
      "return_3y_percent": 5.84,
      "return_5y_percent": 3.95,
      "logo_url": null
    },
    {
      "symbol": "^BVSP",
      "price": 186783.48,
      "change_percent": 1.1,
      "change_7d_percent": -2.4,
      "change_30d_percent": 2.34,
      "return_1y_percent": 38.32,
      "return_3y_percent": 21.38,
      "return_5y_percent": 8.3,
      "logo_url": null
    }
  ],
  "failed_tickers": []
}