{
  "last_updated_utc": "2026-04-24T13:55:40.998737",
  "prices": [
    {
      "symbol": "^GSPC",
      "price": 7115.17,
      "change_percent": -0.3,
      "change_7d_percent": -0.15,
      "change_30d_percent": 8.52,
      "return_1y_percent": 27.78,
      "return_3y_percent": 19.49,
      "return_5y_percent": 11.29,
      "logo_url": null
    },
    {
      "symbol": "^IXIC",
      "price": 24545.25,
      "change_percent": -0.29,
      "change_7d_percent": 0.31,
      "change_30d_percent": 12.79,
      "return_1y_percent": 40.7,
      "return_3y_percent": 26.14,
      "return_5y_percent": 12.51,
      "logo_url": null
    },
    {
      "symbol": "^DJI",
      "price": 49127.13,
      "change_percent": -0.39,
      "change_7d_percent": -0.65,
      "change_30d_percent": 6.51,
      "return_1y_percent": 20.82,
      "return_3y_percent": 12.94,
      "return_5y_percent": 7.43,
      "logo_url": null
    },
    {
      "symbol": "^N225",
      "price": 59716.18,
      "change_percent": 0.52,
      "change_7d_percent": 2.12,
      "change_30d_percent": 14.28,
      "return_1y_percent": 65.73,
      "return_3y_percent": 27.43,
      "return_5y_percent": 15.94,
      "logo_url": null
    },
    {
      "symbol": "^HSI",
      "price": 25978.07,
      "change_percent": 0.95,
      "change_7d_percent": -0.7,
      "change_30d_percent": 3.65,
      "return_1y_percent": 17.46,
      "return_3y_percent": 9.3,
      "return_5y_percent": -2.32,
      "logo_url": null
    },
    {
      "symbol": "^FTSE",
      "price": 10398.31,
      "change_percent": -0.57,
      "change_7d_percent": -2.52,
      "change_30d_percent": 4.35,
      "return_1y_percent": 22.42,
      "return_3y_percent": 9.73,
      "return_5y_percent": 8.31,
      "logo_url": null
    },
    {
      "symbol": "^GDAXI",
      "price": 24154.03,
      "change_percent": -0.26,
      "change_7d_percent": -2.22,
      "change_30d_percent": 6.7,
      "return_1y_percent": 7.37,
      "return_3y_percent": 14.9,
      "return_5y_percent": 9.55,
      "logo_url": null
    },
    {
      "symbol": "^FCHI",
      "price": 8164.38,
      "change_percent": -0.03,
      "change_7d_percent": -3.09,
      "change_30d_percent": 5.43,
      "return_1y_percent": 7.52,
      "return_3y_percent": 2.91,
      "return_5y_percent": 4.92,
      "logo_url": null
    },
    {
      "symbol": "^STOXX50E",
      "price": 5884.74,
      "change_percent": 0.17,
      "change_7d_percent": -2.86,
      "change_30d_percent": 5.44,
      "return_1y_percent": 14.05,
      "return_3y_percent": 10.52,
      "return_5y_percent": 7.95,
      "logo_url": null
    },
    {
      "symbol": "^AXJO",
      "price": 8786.5,
      "change_percent": -0.08,
      "change_7d_percent": -1.79,
      "change_30d_percent": 4.86,
      "return_1y_percent": 8.13,
      "return_3y_percent": 6.33,
      "return_5y_percent": 4.25,
      "logo_url": null
    },
    {
      "symbol": "^BVSP",
      "price": 190332.08,
      "change_percent": -0.55,
      "change_7d_percent": -3.3,
      "change_30d_percent": 4.29,
      "return_1y_percent": 40.95,
      "return_3y_percent": 22.14,
      "return_5y_percent": 8.71,
      "logo_url": null
    }
  ],
  "failed_tickers": []
}