{
  "last_updated_utc": "2026-04-14T12:04:26.470631",
  "prices": [
    {
      "symbol": "GC=F",
      "price": 4796.6,
      "change_percent": 0.57,
      "change_7d_percent": 3.0,
      "change_30d_percent": -3.95,
      "return_1y_percent": 53.5,
      "return_3y_percent": 34.43,
      "return_5y_percent": null,
      "logo_url": "https://raw.githubusercontent.com/mickomagallanes/aiahlyze-backend/refs/heads/main/gold.png"
    },
    {
      "symbol": "SI=F",
      "price": 77.57,
      "change_percent": 2.53,
      "change_7d_percent": 8.0,
      "change_30d_percent": -3.36,
      "return_1y_percent": 102.91,
      "return_3y_percent": 48.2,
      "return_5y_percent": null,
      "logo_url": "https://raw.githubusercontent.com/mickomagallanes/aiahlyze-backend/refs/heads/main/silver.png"
    },
    {
      "symbol": "CL=F",
      "price": 97.28,
      "change_percent": -0.72,
      "change_7d_percent": -13.87,
      "change_30d_percent": 4.04,
      "return_1y_percent": 26.58,
      "return_3y_percent": 5.8,
      "return_5y_percent": null,
      "logo_url": "https://raw.githubusercontent.com/mickomagallanes/aiahlyze-backend/refs/heads/main/oil.png"
    },
    {
      "symbol": "BZ=F",
      "price": 99.01,
      "change_percent": 0.6,
      "change_7d_percent": -9.39,
      "change_30d_percent": -1.2,
      "return_1y_percent": 22.67,
      "return_3y_percent": 3.36,
      "return_5y_percent": null,
      "logo_url": "https://raw.githubusercontent.com/mickomagallanes/aiahlyze-backend/refs/heads/main/brent.png"
    },
    {
      "symbol": "NG=F",
      "price": 2.6,
      "change_percent": -1.03,
      "change_7d_percent": -9.37,
      "change_30d_percent": -13.96,
      "return_1y_percent": -11.86,
      "return_3y_percent": -23.43,
      "return_5y_percent": null,
      "logo_url": "https://raw.githubusercontent.com/mickomagallanes/aiahlyze-backend/refs/heads/main/natural-gas.png"
    },
    {
      "symbol": "HG=F",
      "price": 6.03,
      "change_percent": 0.51,
      "change_7d_percent": 8.83,
      "change_30d_percent": 4.21,
      "return_1y_percent": 32.19,
      "return_3y_percent": 16.97,
      "return_5y_percent": null,
      "logo_url": "https://raw.githubusercontent.com/mickomagallanes/aiahlyze-backend/refs/heads/main/copper.png"
    },
    {
      "symbol": "PL=F",
      "price": 2089.7,
      "change_percent": 0.18,
      "change_7d_percent": 8.33,
      "change_30d_percent": 0.01,
      "return_1y_percent": 76.02,
      "return_3y_percent": 27.72,
      "return_5y_percent": null,
      "logo_url": "https://raw.githubusercontent.com/mickomagallanes/aiahlyze-backend/refs/heads/main/platinum.png"
    },
    {
      "symbol": "PA=F",
      "price": 1591.0,
      "change_percent": -0.06,
      "change_7d_percent": 10.33,
      "change_30d_percent": 0.41,
      "return_1y_percent": 37.82,
      "return_3y_percent": -8.34,
      "return_5y_percent": null,
      "logo_url": "https://raw.githubusercontent.com/mickomagallanes/aiahlyze-backend/refs/heads/main/palladium.png"
    }
  ],
  "failed_tickers": []
}