{
  "last_updated_utc": "2026-04-01T11:08:19.888168",
  "prices": [
    {
      "symbol": "GC=F",
      "price": 4756.6,
      "change_percent": 1.24,
      "change_7d_percent": 4.55,
      "change_30d_percent": -10.16,
      "logo_url": "https://raw.githubusercontent.com/mickomagallanes/aiahlyze-backend/refs/heads/main/gold.png"
    },
    {
      "symbol": "SI=F",
      "price": 74.97,
      "change_percent": -0.67,
      "change_7d_percent": 3.61,
      "change_30d_percent": -15.08,
      "logo_url": "https://raw.githubusercontent.com/mickomagallanes/aiahlyze-backend/refs/heads/main/silver.png"
    },
    {
      "symbol": "CL=F",
      "price": 100.12,
      "change_percent": -1.57,
      "change_7d_percent": 10.85,
      "change_30d_percent": 40.56,
      "logo_url": "https://raw.githubusercontent.com/mickomagallanes/aiahlyze-backend/refs/heads/main/oil.png"
    },
    {
      "symbol": "BZ=F",
      "price": 103.17,
      "change_percent": -0.7,
      "change_7d_percent": 0.93,
      "change_30d_percent": 32.71,
      "logo_url": "https://raw.githubusercontent.com/mickomagallanes/aiahlyze-backend/refs/heads/main/brent.png"
    },
    {
      "symbol": "NG=F",
      "price": 2.85,
      "change_percent": -1.08,
      "change_7d_percent": -3.49,
      "change_30d_percent": -3.75,
      "logo_url": "https://raw.githubusercontent.com/mickomagallanes/aiahlyze-backend/refs/heads/main/natural-gas.png"
    },
    {
      "symbol": "HG=F",
      "price": 5.63,
      "change_percent": -0.35,
      "change_7d_percent": 1.8,
      "change_30d_percent": -4.51,
      "logo_url": "https://raw.githubusercontent.com/mickomagallanes/aiahlyze-backend/refs/heads/main/copper.png"
    },
    {
      "symbol": "PL=F",
      "price": 1967.3,
      "change_percent": -0.06,
      "change_7d_percent": 2.19,
      "change_30d_percent": -14.91,
      "logo_url": "https://raw.githubusercontent.com/mickomagallanes/aiahlyze-backend/refs/heads/main/platinum.png"
    },
    {
      "symbol": "PA=F",
      "price": 1487.5,
      "change_percent": -0.3,
      "change_7d_percent": 5.05,
      "change_30d_percent": -15.61,
      "logo_url": "https://raw.githubusercontent.com/mickomagallanes/aiahlyze-backend/refs/heads/main/palladium.png"
    }
  ],
  "failed_tickers": []
}